bikit/__init__.py
bikit/datasets.py
bikit/metrics.py
bikit/models.py
bikit/utils.py
bikit/data/__init__.py
bikit/data/bcd.csv
bikit/data/cds.csv
bikit/data/codebrim-classif-balanced.csv
bikit/data/codebrim-classif.csv
bikit/data/dacl1k.csv
bikit/data/datasets.json
bikit/data/mcds.csv
bikit/data/mcds_Bukhsh.csv
bikit/data/mcds_bikit.csv
bikit/data/meta2.csv
bikit/data/meta3+dacl1k.csv
bikit/data/meta3.csv
bikit/data/meta4+dacl1k.csv
bikit/data/meta4.csv
bikit/data/sdnet.csv
bikit/data/sdnet_bikit.csv
bikit/data/sdnet_bikit_binary.csv
bikit/data/sdnet_binary.csv
tests/__init__.py
tests/test_bcd.py
tests/test_cds.py
tests/test_codebrim.py
tests/test_mcds.py
tests/test_sdnet.py
tests/test_utils.py
building_inspection_toolkit-0.1.6.dist-info/LICENSE
building_inspection_toolkit-0.1.6.dist-info/METADATA
building_inspection_toolkit-0.1.6.dist-info/WHEEL
building_inspection_toolkit-0.1.6.dist-info/top_level.txt
building_inspection_toolkit-0.1.6.dist-info/RECORD
