Metadata-Version: 2.1
Name: building-inspection-toolkit
Version: 0.1.6
Summary: Building Inspection Toolkit
Home-page: https://github.com/phiyodr/bridge-inspection-toolkit
Author: Philipp J. Roesch, Johannes Flotzinger
Author-email: philipp.roesch@unibw.de, johannes.flotzinger@unibw.de
License: UNKNOWN
Platform: UNKNOWN
Classifier: Programming Language :: Python :: 3
Classifier: Topic :: Scientific/Engineering :: Artificial Intelligence
Classifier: Topic :: Scientific/Engineering :: Image Recognition
Requires-Python: >=3.6
License-File: LICENSE
Requires-Dist: numpy (>1.20requeststorchtorchvisionpandasPillowpatoolpathlibtqdmmatplotlibopencv-python-headlessefficientnet_pytorchtorchmetrics)
